aiotgbot/__init__.py
aiotgbot/_version.py
aiotgbot/api_methods.py
aiotgbot/api_types.py
aiotgbot/bot.py
aiotgbot/bot_update.py
aiotgbot/constants.py
aiotgbot/exceptions.py
aiotgbot/filters.py
aiotgbot/handler_table.py
aiotgbot/helpers.py
aiotgbot/listen_bot.py
aiotgbot/passport.py
aiotgbot/py.typed
aiotgbot/storage.py
aiotgbot/storage_memory.py
aiotgbot/storage_sqlalchemy.py
aiotgbot/storage_sqlite.py
aiotgbot-0.18.3.dist-info/WHEEL
aiotgbot-0.18.3.dist-info/METADATA
aiotgbot-0.18.3.dist-info/RECORD
