Metadata-Version: 2.3
Name: aiotgbot
Version: 0.18.3
Summary: Asynchronous library for Telegram bot API
Author: Gleb Chipiga
License: MIT License
Classifier: Intended Audience :: Developers
Classifier: Programming Language :: Python
Classifier: Programming Language :: Python :: 3
Classifier: Programming Language :: Python :: 3.11
Classifier: Programming Language :: Python :: 3.12
Classifier: Programming Language :: Python :: 3.13
Classifier: License :: OSI Approved :: MIT License
Classifier: Development Status :: 4 - Beta
Classifier: Operating System :: POSIX
Classifier: Operating System :: MacOS :: MacOS X
Classifier: Operating System :: Microsoft :: Windows
Classifier: Topic :: Internet
Classifier: Topic :: Communications :: Chat
Classifier: Framework :: AsyncIO
Requires-Dist: aiofreqlimit>=0.0.16
Requires-Dist: aiohttp>=3.13.2
Requires-Dist: aiojobs>=1.4.0
Requires-Dist: backoff>=2.2.1
Requires-Dist: frozenlist>=1.8.0
Requires-Dist: msgspec>=0.19.0
Requires-Dist: yarl>=1.22.0
Requires-Dist: cryptography>=46.0.0 ; extra == 'passport'
Requires-Dist: sqlalchemy ; extra == 'sqlalchemy'
Requires-Dist: aiosqlite ; extra == 'sqlite'
Requires-Python: >=3.11, <3.14
Project-URL: Homepage, https://github.com/gleb-chipiga/aiotgbot
Provides-Extra: passport
Provides-Extra: sqlalchemy
Provides-Extra: sqlite
